SparkBoot/__init__.py
SparkBoot/boot.py
SparkBoot/main.py
SparkBoot/run.py
SparkBoot-1.0.0.dist-info/METADATA
SparkBoot-1.0.0.dist-info/WHEEL
SparkBoot-1.0.0.dist-info/entry_points.txt
SparkBoot-1.0.0.dist-info/top_level.txt
SparkBoot-1.0.0.dist-info/RECORD
